[{"name":"Abovyan","country":"AM","lat":40.2717,"lon":44.63342},{"name":"Abovyan","country":"AM","lat":40.04851,"lon":44.54742},{"name":"Achajur","country":"AM","lat":40.98781,"lon":45.14952},{"name":"Agarak","country":"AM","lat":38.86506,"lon":46.19463},{"name":"Agarak","country":"AM","lat":41.01072,"lon":44.46845},{"name":"Agarak","country":"AM","lat":40.30191,"lon":44.27923},{"name":"Agarakadzor","country":"AM","lat":39.73608,"lon":45.35553},{"name":"Agarakavan","country":"AM","lat":40.33069,"lon":44.07233},{"name":"Aghavnadzor","country":"AM","lat":39.78197,"lon":45.22708},{"name":"Aghavnadzor","country":"AM","lat":40.57848,"lon":44.69948},{"name":"Aghavnatun","country":"AM","lat":40.2333,"lon":44.25295},{"name":"Aghdzk","country":"AM","lat":40.3139,"lon":44.25568},{"name":"Ajapnyak","country":"AM","lat":40.19917,"lon":44.47056},{"name":"Akhtala","country":"AM","lat":41.14952,"lon":44.78168},{"name":"Akhurik","country":"AM","lat":40.74212,"lon":43.77674},{"name":"Akhuryan","country":"AM","lat":40.78081,"lon":43.90037},{"name":"Aknalich","country":"AM","lat":40.14728,"lon":44.16669},{"name":"Aknashen","country":"AM","lat":40.09275,"lon":44.29157},{"name":"Akner","country":"AM","lat":39.53491,"lon":46.30732},{"name":"Akori","country":"AM","lat":41.08976,"lon":44.6173},{"name":"Akunk","country":"AM","lat":40.26672,"lon":44.6861},{"name":"Akunk","country":"AM","lat":40.16056,"lon":45.72707},{"name":"Alagyaz","country":"AM","lat":40.68082,"lon":44.28797},{"name":"Alapars","country":"AM","lat":40.4223,"lon":44.63348},{"name":"Alashkert","country":"AM","lat":40.10712,"lon":44.05108},{"name":"Alaverdi","country":"AM","lat":41.09766,"lon":44.67316},{"name":"Amasia","country":"AM","lat":40.08331,"lon":43.96668},{"name":"Amasia","country":"AM","lat":40.95566,"lon":43.78379},{"name":"Amberd","country":"AM","lat":40.24177,"lon":44.27128},{"name":"Angeghakot","country":"AM","lat":39.56952,"lon":45.94452},{"name":"Anushavan","country":"AM","lat":40.65008,"lon":43.98053},{"name":"Apaga","country":"AM","lat":40.09729,"lon":44.25293},{"name":"Aparan","country":"AM","lat":40.59297,"lon":44.35945},{"name":"Arabkir","country":"AM","lat":40.20624,"lon":44.50365},{"name":"Aragats","country":"AM","lat":40.48889,"lon":44.3529},{"name":"Aragats","country":"AM","lat":40.21948,"lon":44.23328},{"name":"Aragatsavan","country":"AM","lat":40.32121,"lon":43.66205},{"name":"Aragyugh","country":"AM","lat":40.40289,"lon":44.54449},{"name":"Araks","country":"AM","lat":40.05548,"lon":44.30292},{"name":"Araks","country":"AM","lat":40.09729,"lon":43.95569},{"name":"Aralez","country":"AM","lat":39.90005,"lon":44.65086},{"name":"Aramus","country":"AM","lat":40.25095,"lon":44.66351},{"name":"Arapi","country":"AM","lat":40.78276,"lon":43.80583},{"name":"Ararat","country":"AM","lat":39.85494,"lon":44.6947},{"name":"Ararat village","country":"AM","lat":39.83166,"lon":44.70489},{"name":"Aratashen","country":"AM","lat":40.12824,"lon":44.22803},{"name":"Arazap","country":"AM","lat":40.04169,"lon":44.14728},{"name":"Arbat","country":"AM","lat":40.13892,"lon":44.40289},{"name":"Archis","country":"AM","lat":41.16351,"lon":44.87631},{"name":"Areni","country":"AM","lat":39.72205,"lon":45.18392},{"name":"Arevabuyr","country":"AM","lat":40.03607,"lon":44.46948},{"name":"Arevashat","country":"AM","lat":40.13984,"lon":44.3744},{"name":"Arevashogh","country":"AM","lat":40.86039,"lon":44.27438},{"name":"Arevik","country":"AM","lat":40.7417,"lon":43.9043},{"name":"Arevik","country":"AM","lat":40.1001,"lon":44.09448},{"name":"Arevshat","country":"AM","lat":40.65345,"lon":44.04419},{"name":"Arevshat","country":"AM","lat":40.03963,"lon":44.54179},{"name":"Arevut","country":"AM","lat":40.36394,"lon":43.81025},{"name":"Argavand","country":"AM","lat":40.15289,"lon":44.4389},{"name":"Argavand","country":"AM","lat":40.0611,"lon":44.09448},{"name":"Argel","country":"AM","lat":40.37116,"lon":44.59618},{"name":"Arinj","country":"AM","lat":40.23356,"lon":44.58209},{"name":"Arjut","country":"AM","lat":40.86118,"lon":44.37587},{"name":"Armash","country":"AM","lat":39.76672,"lon":44.8111},{"name":"Armavir","country":"AM","lat":40.15446,"lon":44.03815},{"name":"Armavir","country":"AM","lat":40.08298,"lon":44.05777},{"name":"Arpi","country":"AM","lat":39.73889,"lon":45.26672},{"name":"Arshaluys","country":"AM","lat":40.16949,"lon":44.21393},{"name":"Artashar","country":"AM","lat":40.11108,"lon":44.18329},{"name":"Artashat","country":"AM","lat":39.95484,"lon":44.54874},{"name":"Arteni","country":"AM","lat":40.2973,"lon":43.76672},{"name":"Artik","country":"AM","lat":40.61918,"lon":43.97207},{"name":"Artimet","country":"AM","lat":40.15008,"lon":44.26672},{"name":"Artsvaberd","country":"AM","lat":40.83947,"lon":45.47033},{"name":"Artsvanist","country":"AM","lat":40.14857,"lon":45.50874},{"name":"Aruch","country":"AM","lat":40.28749,"lon":44.07798},{"name":"Arzakan","country":"AM","lat":40.45007,"lon":44.60828},{"name":"Arzni","country":"AM","lat":40.29636,"lon":44.5958},{"name":"Ashnak","country":"AM","lat":40.33069,"lon":43.91669},{"name":"Ashotsk","country":"AM","lat":41.0377,"lon":43.85843},{"name":"Ashtarak","country":"AM","lat":40.2991,"lon":44.36204},{"name":"Astghadzor","country":"AM","lat":40.12231,"lon":45.35553},{"name":"Avan","country":"AM","lat":40.21436,"lon":44.57846},{"name":"Avshar","country":"AM","lat":39.85388,"lon":44.68016},{"name":"Aygavan","country":"AM","lat":39.87327,"lon":44.66984},{"name":"Aygedzor","country":"AM","lat":40.83121,"lon":45.54483},{"name":"Aygehovit","country":"AM","lat":40.97951,"lon":45.25033},{"name":"Aygek","country":"AM","lat":40.1889,"lon":44.38611},{"name":"Aygepat","country":"AM","lat":39.95565,"lon":44.59181},{"name":"Aygeshat","country":"AM","lat":40.23608,"lon":44.28888},{"name":"Aygeshat","country":"AM","lat":40.07507,"lon":44.0611},{"name":"Aygestan","country":"AM","lat":40.00293,"lon":44.55829},{"name":"Aygevan","country":"AM","lat":40.14172,"lon":43.9751},{"name":"Aygezard","country":"AM","lat":39.95436,"lon":44.60229},{"name":"Ayntap","country":"AM","lat":40.09659,"lon":44.4646},{"name":"Ayrum","country":"AM","lat":41.18826,"lon":44.90404},{"name":"Azatamut","country":"AM","lat":40.98847,"lon":45.2067},{"name":"Azatan","country":"AM","lat":40.71959,"lon":43.82727},{"name":"Azatavan","country":"AM","lat":39.98608,"lon":44.50568},{"name":"Baghramyan","country":"AM","lat":39.98053,"lon":44.51392},{"name":"Baghramyan","country":"AM","lat":40.19608,"lon":43.85409},{"name":"Baghramyan","country":"AM","lat":40.19324,"lon":44.36934},{"name":"Bagratashen","country":"AM","lat":41.24358,"lon":44.81737},{"name":"Balahovit","country":"AM","lat":40.25153,"lon":44.60828},{"name":"Bardzrashen","country":"AM","lat":40.08533,"lon":44.57957},{"name":"Basen","country":"AM","lat":40.75767,"lon":43.99274},{"name":"Bazmaghbyur","country":"AM","lat":40.3295,"lon":44.319},{"name":"Bazum","country":"AM","lat":40.86763,"lon":44.43978},{"name":"Berd","country":"AM","lat":40.88066,"lon":45.38901},{"name":"Berdavan","country":"AM","lat":41.20503,"lon":44.99967},{"name":"Berkanush","country":"AM","lat":39.97729,"lon":44.52127},{"name":"Bjni","country":"AM","lat":40.45382,"lon":44.64841},{"name":"Brnakot","country":"AM","lat":39.49742,"lon":45.97241},{"name":"Burastan","country":"AM","lat":39.98907,"lon":44.49785},{"name":"Buzhakan","country":"AM","lat":40.45569,"lon":44.51947},{"name":"Byurakan","country":"AM","lat":40.33894,"lon":44.27275},{"name":"Byuravan","country":"AM","lat":40.01604,"lon":44.51889},{"name":"Byureghavan","country":"AM","lat":40.31335,"lon":44.59685},{"name":"Chambarak","country":"AM","lat":40.59655,"lon":45.35498},{"name":"Charentsavan","country":"AM","lat":40.40289,"lon":44.64447},{"name":"Chochkan","country":"AM","lat":41.18118,"lon":44.83217},{"name":"Dalar","country":"AM","lat":39.97539,"lon":44.52784},{"name":"Dalarik","country":"AM","lat":40.22648,"lon":43.8719},{"name":"Darakert","country":"AM","lat":40.10553,"lon":44.41388},{"name":"Darbnik","country":"AM","lat":40.10828,"lon":44.37793},{"name":"Darpas","country":"AM","lat":40.83674,"lon":44.42494},{"name":"Dashtavan","country":"AM","lat":40.1001,"lon":44.39172},{"name":"Davtashen","country":"AM","lat":40.21642,"lon":44.48088},{"name":"Ddmashen","country":"AM","lat":40.57013,"lon":44.81609},{"name":"Dilijan","country":"AM","lat":40.74037,"lon":44.86344},{"name":"Dimitrov","country":"AM","lat":40.00848,"lon":44.4917},{"name":"Doghs","country":"AM","lat":40.22229,"lon":44.27228},{"name":"Dsegh","country":"AM","lat":40.9617,"lon":44.65003},{"name":"Dvin","country":"AM","lat":40.01984,"lon":44.58376},{"name":"Dzithankov","country":"AM","lat":40.50848,"lon":43.82092},{"name":"Dzoraghbyur","country":"AM","lat":40.2004,"lon":44.63438},{"name":"Dzoragyugh","country":"AM","lat":40.16817,"lon":45.1945},{"name":"Dzorakap","country":"AM","lat":40.56811,"lon":43.88068},{"name":"Erebuni","country":"AM","lat":40.13309,"lon":44.53009},{"name":"Ferik","country":"AM","lat":40.1874,"lon":44.20952},{"name":"Fioletovo","country":"AM","lat":40.72365,"lon":44.71664},{"name":"Gagarin","country":"AM","lat":40.54026,"lon":44.86962},{"name":"Gandzak","country":"AM","lat":40.32309,"lon":45.1103},{"name":"Gandzakar","country":"AM","lat":40.84291,"lon":45.16132},{"name":"Gargar","country":"AM","lat":40.9577,"lon":44.44161},{"name":"Garni","country":"AM","lat":40.11931,"lon":44.73442},{"name":"Gavar","country":"AM","lat":40.35398,"lon":45.12386},{"name":"Gay","country":"AM","lat":40.08444,"lon":44.30528},{"name":"Geghadzor","country":"AM","lat":40.62731,"lon":44.17095},{"name":"Geghakert","country":"AM","lat":40.18516,"lon":44.24493},{"name":"Geghamavan","country":"AM","lat":40.5625,"lon":44.88892},{"name":"Geghanist","country":"AM","lat":40.68467,"lon":44.02333},{"name":"Geghanist","country":"AM","lat":40.14587,"lon":44.43048},{"name":"Gegharkunik","country":"AM","lat":40.25568,"lon":45.14728},{"name":"Geghashen","country":"AM","lat":40.22754,"lon":44.72464},{"name":"Geghhovit","country":"AM","lat":40.10479,"lon":45.2855},{"name":"Getahovit","country":"AM","lat":40.89523,"lon":45.1355},{"name":"Getap","country":"AM","lat":39.76392,"lon":45.30829},{"name":"Getapnya","country":"AM","lat":40.1381,"lon":44.42795},{"name":"Getashen","country":"AM","lat":40.04449,"lon":43.94171},{"name":"Getazat","country":"AM","lat":40.03844,"lon":44.56369},{"name":"Ghukasavan","country":"AM","lat":40.12394,"lon":44.41556},{"name":"Gladzor","country":"AM","lat":39.7807,"lon":45.34729},{"name":"Gogaran","country":"AM","lat":40.89255,"lon":44.19915},{"name":"Goght","country":"AM","lat":40.1347,"lon":44.78332},{"name":"Goravan","country":"AM","lat":39.90539,"lon":44.73131},{"name":"Goris","country":"AM","lat":39.51111,"lon":46.34168},{"name":"Gosh","country":"AM","lat":40.73053,"lon":45.00012},{"name":"Griboyedov","country":"AM","lat":40.11307,"lon":44.27169},{"name":"Gugark","country":"AM","lat":40.8046,"lon":44.54025},{"name":"Gyulagarak","country":"AM","lat":40.96528,"lon":44.47128},{"name":"Gyumri","country":"AM","lat":40.7942,"lon":43.84528},{"name":"Haghartsin","country":"AM","lat":40.77614,"lon":44.96847},{"name":"Haghtanak","country":"AM","lat":41.2172,"lon":44.91376},{"name":"Harich","country":"AM","lat":40.60947,"lon":44.00308},{"name":"Hartagyugh","country":"AM","lat":40.8346,"lon":44.04614},{"name":"Hatsik","country":"AM","lat":40.17143,"lon":43.94993},{"name":"Hayanist","country":"AM","lat":40.11995,"lon":44.37298},{"name":"Haykashen","country":"AM","lat":40.07233,"lon":44.30829},{"name":"Haykavan","country":"AM","lat":40.80312,"lon":43.75173},{"name":"Haykavan","country":"AM","lat":40.08893,"lon":44.03888},{"name":"Haytagh","country":"AM","lat":40.18048,"lon":44.23328},{"name":"Hnaberd","country":"AM","lat":40.63721,"lon":44.14058},{"name":"Horom","country":"AM","lat":40.65973,"lon":43.89032},{"name":"Hovtamej","country":"AM","lat":40.18249,"lon":44.25383},{"name":"Hovtashat","country":"AM","lat":40.09729,"lon":44.34448},{"name":"Hovtashen","country":"AM","lat":40.02508,"lon":44.45007},{"name":"Hrazdan","country":"AM","lat":40.5169,"lon":44.75591},{"name":"Hushakert","country":"AM","lat":40.08331,"lon":43.93048},{"name":"Ijevan","country":"AM","lat":40.87877,"lon":45.14851},{"name":"Isahakyan","country":"AM","lat":40.61564,"lon":43.72643},{"name":"Janfida","country":"AM","lat":40.04449,"lon":44.02789},{"name":"Jermuk","country":"AM","lat":39.83948,"lon":45.67112},{"name":"Jrahovit","country":"AM","lat":40.0473,"lon":44.4751},{"name":"Jrarat","country":"AM","lat":40.73817,"lon":44.02776},{"name":"Jrarat","country":"AM","lat":40.07214,"lon":44.27137},{"name":"Jrarbi","country":"AM","lat":40.08738,"lon":44.23995},{"name":"Jrashen","country":"AM","lat":40.79028,"lon":44.18664},{"name":"Jrashen","country":"AM","lat":40.05275,"lon":44.51259},{"name":"Jrvezh","country":"AM","lat":40.18889,"lon":44.62414},{"name":"Kaghsi","country":"AM","lat":40.47196,"lon":44.73744},{"name":"Kaghtsrashen","country":"AM","lat":39.98053,"lon":44.62512},{"name":"Kajaran","country":"AM","lat":39.15091,"lon":46.15673},{"name":"Kakavadzor","country":"AM","lat":40.35406,"lon":44.05435},{"name":"Kamaris","country":"AM","lat":40.23694,"lon":44.69153},{"name":"Kamo","country":"AM","lat":40.82572,"lon":43.95071},{"name":"Kanachut","country":"AM","lat":40.0095,"lon":44.54531},{"name":"Kanaker-Zeytun","country":"AM","lat":40.22,"lon":44.53833},{"name":"Kanakeravan","country":"AM","lat":40.24739,"lon":44.53511},{"name":"Kapan","country":"AM","lat":39.20755,"lon":46.40576},{"name":"Kaputan","country":"AM","lat":40.32507,"lon":44.70007},{"name":"Karaberd","country":"AM","lat":40.54309,"lon":43.83331},{"name":"Karahunj","country":"AM","lat":39.47383,"lon":46.35963},{"name":"Karakert","country":"AM","lat":40.24451,"lon":43.82233},{"name":"Karanlukh","country":"AM","lat":40.10444,"lon":45.28972},{"name":"Karbi","country":"AM","lat":40.33069,"lon":44.37793},{"name":"Karchaghbyur","country":"AM","lat":40.17048,"lon":45.57785},{"name":"Karin","country":"AM","lat":40.25,"lon":44.33},{"name":"Karmirgyugh","country":"AM","lat":40.33103,"lon":45.14598},{"name":"Karnut","country":"AM","lat":40.7836,"lon":43.95695},{"name":"Kasakh","country":"AM","lat":40.53697,"lon":44.41046},{"name":"Kasakh","country":"AM","lat":40.23555,"lon":44.45162},{"name":"Katnaghbyur","country":"AM","lat":40.38068,"lon":43.94733},{"name":"Katnajur","country":"AM","lat":40.82323,"lon":44.14137},{"name":"Kentron","country":"AM","lat":40.17806,"lon":44.51303},{"name":"Keti","country":"AM","lat":40.87415,"lon":43.84822},{"name":"Khachaghbyur","country":"AM","lat":40.16808,"lon":45.69259},{"name":"Khachpar","country":"AM","lat":40.12512,"lon":44.4057},{"name":"Khanjyan","country":"AM","lat":40.18742,"lon":43.97718},{"name":"Khashtarak","country":"AM","lat":40.93668,"lon":45.1821},{"name":"Khndzoresk","country":"AM","lat":39.51325,"lon":46.43141},{"name":"Khoronk","country":"AM","lat":40.13611,"lon":44.24731},{"name":"Koghb","country":"AM","lat":41.18184,"lon":44.97608},{"name":"Kornidzor","country":"AM","lat":39.54763,"lon":46.53046},{"name":"Kosh","country":"AM","lat":40.29995,"lon":44.15252},{"name":"Kotayk","country":"AM","lat":40.27789,"lon":44.66388},{"name":"Koti","country":"AM","lat":41.13243,"lon":45.1295},{"name":"Kuchak","country":"AM","lat":40.51915,"lon":44.39119},{"name":"Kurtan","country":"AM","lat":40.95719,"lon":44.55623},{"name":"Lanjaghbyur","country":"AM","lat":40.26947,"lon":45.14447},{"name":"Lanjazat","country":"AM","lat":40.06102,"lon":44.57544},{"name":"Lchap","country":"AM","lat":40.45569,"lon":45.07507},{"name":"Lchashen","country":"AM","lat":40.51947,"lon":44.93048},{"name":"Lenughi","country":"AM","lat":40.12512,"lon":43.96393},{"name":"Lermontovo","country":"AM","lat":40.75843,"lon":44.63401},{"name":"Lernagog","country":"AM","lat":40.24011,"lon":43.87102},{"name":"Lernahovit","country":"AM","lat":41.1619,"lon":44.36979},{"name":"Lernakert","country":"AM","lat":40.5625,"lon":43.9389},{"name":"Lernanist","country":"AM","lat":40.46676,"lon":44.79249},{"name":"Lernantsk","country":"AM","lat":40.79532,"lon":44.27435},{"name":"Lernapat","country":"AM","lat":40.81538,"lon":44.39344},{"name":"Lernavan","country":"AM","lat":40.7882,"lon":44.16024},{"name":"Lichk","country":"AM","lat":40.15933,"lon":45.23467},{"name":"Lukashin","country":"AM","lat":40.18726,"lon":44.0039},{"name":"Lusaghbyur","country":"AM","lat":40.86137,"lon":44.03489},{"name":"Lusagyugh","country":"AM","lat":40.08893,"lon":44.26947},{"name":"Lusakunk","country":"AM","lat":40.1778,"lon":45.69137},{"name":"Lusarat","country":"AM","lat":39.87403,"lon":44.58678},{"name":"Madina","country":"AM","lat":40.07637,"lon":45.25507},{"name":"Malatia-Sebastia","country":"AM","lat":40.17396,"lon":44.4457},{"name":"Malishka","country":"AM","lat":39.73787,"lon":45.39058},{"name":"Maralik","country":"AM","lat":40.57595,"lon":43.87059},{"name":"Margahovit","country":"AM","lat":40.73381,"lon":44.68474},{"name":"Margara","country":"AM","lat":40.03332,"lon":44.18048},{"name":"Marmarashen","country":"AM","lat":40.05829,"lon":44.47229},{"name":"Marmashen","country":"AM","lat":40.83486,"lon":43.7779},{"name":"Martuni","country":"AM","lat":40.14028,"lon":45.30232},{"name":"Masis","country":"AM","lat":40.06595,"lon":44.43669},{"name":"Masis","country":"AM","lat":39.99772,"lon":44.49349},{"name":"Mastara","country":"AM","lat":40.4471,"lon":43.8817},{"name":"Mayakovski","country":"AM","lat":40.24419,"lon":44.6341},{"name":"Mayisyan","country":"AM","lat":40.84715,"lon":43.83938},{"name":"Mayisyan","country":"AM","lat":40.15701,"lon":44.09192},{"name":"Meghradzor","country":"AM","lat":40.6068,"lon":44.64158},{"name":"Meghrashen","country":"AM","lat":40.67017,"lon":43.95652},{"name":"Meghri","country":"AM","lat":38.90123,"lon":46.24308},{"name":"Melikgyugh","country":"AM","lat":40.66545,"lon":44.35358},{"name":"Merdzavan","country":"AM","lat":40.1814,"lon":44.40033},{"name":"Mets Mantash","country":"AM","lat":40.64376,"lon":44.05653},{"name":"Mets Masrik","country":"AM","lat":40.21948,"lon":45.76391},{"name":"Mets Parni","country":"AM","lat":40.83472,"lon":44.11108},{"name":"Metsadzor","country":"AM","lat":40.38036,"lon":44.04591},{"name":"Metsamor","country":"AM","lat":40.07246,"lon":44.2905},{"name":"Metsamor","country":"AM","lat":40.14459,"lon":44.11484},{"name":"Metsavan","country":"AM","lat":41.20156,"lon":44.22877},{"name":"Mkhchyan","country":"AM","lat":40.02228,"lon":44.4917},{"name":"Movses","country":"AM","lat":40.90534,"lon":45.48838},{"name":"Mrganush","country":"AM","lat":40.02642,"lon":44.55953},{"name":"Mrgashat","country":"AM","lat":40.13068,"lon":44.08069},{"name":"Mrgashen","country":"AM","lat":40.28607,"lon":44.54449},{"name":"Mrgastan","country":"AM","lat":40.20007,"lon":44.27789},{"name":"Mrgavan","country":"AM","lat":39.97251,"lon":44.53565},{"name":"Mrgavet","country":"AM","lat":40.02789,"lon":44.48328},{"name":"Mughni","country":"AM","lat":40.31198,"lon":44.36671},{"name":"Musaler","country":"AM","lat":40.1557,"lon":44.37793},{"name":"Myasnikyan","country":"AM","lat":40.18048,"lon":43.91949},{"name":"Nalbandyan","country":"AM","lat":40.0639,"lon":43.98889},{"name":"Narek","country":"AM","lat":40.00041,"lon":44.66482},{"name":"Navur","country":"AM","lat":40.86695,"lon":45.34179},{"name":"Nerkin Bazmaberd","country":"AM","lat":40.33893,"lon":44.01392},{"name":"Nerkin Getashen","country":"AM","lat":40.14172,"lon":45.27087},{"name":"Nerkin Sasnashen","country":"AM","lat":40.35553,"lon":43.9917},{"name":"Nizami","country":"AM","lat":40.09168,"lon":44.4057},{"name":"Nor Armavir","country":"AM","lat":40.08612,"lon":43.99451},{"name":"Nor Artagers","country":"AM","lat":40.06952,"lon":44.00568},{"name":"Nor Artamet","country":"AM","lat":40.30046,"lon":44.55787},{"name":"Nor Geghi","country":"AM","lat":40.31668,"lon":44.57785},{"name":"Nor Gyugh","country":"AM","lat":40.26494,"lon":44.65471},{"name":"Nor Hachn","country":"AM","lat":40.30296,"lon":44.58314},{"name":"Nor Kesaria","country":"AM","lat":40.05941,"lon":43.90725},{"name":"Nor Kharberd","country":"AM","lat":40.09168,"lon":44.48053},{"name":"Nor Kyank","country":"AM","lat":39.902,"lon":44.63},{"name":"Nor Kyank","country":"AM","lat":40.65832,"lon":43.93189},{"name":"Nor Kyurin","country":"AM","lat":40.07386,"lon":44.49731},{"name":"Nor Nork","country":"AM","lat":40.19661,"lon":44.5669},{"name":"Nor Yedesia","country":"AM","lat":40.22229,"lon":44.13348},{"name":"Nor Yerznka","country":"AM","lat":40.30011,"lon":44.38892},{"name":"Norabats","country":"AM","lat":40.10553,"lon":44.43329},{"name":"Norakert","country":"AM","lat":40.19733,"lon":44.3501},{"name":"Noramarg","country":"AM","lat":40.02228,"lon":44.42511},{"name":"Norapat","country":"AM","lat":40.14172,"lon":44.03332},{"name":"Norashen","country":"AM","lat":40.87683,"lon":45.45722},{"name":"Norashen","country":"AM","lat":40.65722,"lon":44.07702},{"name":"Norashen","country":"AM","lat":40.0013,"lon":44.59296},{"name":"Noratus","country":"AM","lat":40.37793,"lon":45.18048},{"name":"Noravan","country":"AM","lat":40.17244,"lon":44.02979},{"name":"Nork-Marash","country":"AM","lat":40.17417,"lon":44.54083},{"name":"Noyakert","country":"AM","lat":39.83069,"lon":44.66949},{"name":"Noyemberyan","country":"AM","lat":41.17319,"lon":44.99851},{"name":"Nshavan","country":"AM","lat":40.02787,"lon":44.52565},{"name":"Nubarashen","country":"AM","lat":40.09075,"lon":44.5519},{"name":"Odzun","country":"AM","lat":41.05321,"lon":44.61341},{"name":"Ohanavan","country":"AM","lat":40.3485,"lon":44.38717},{"name":"Oshakan","country":"AM","lat":40.26392,"lon":44.31671},{"name":"Panik","country":"AM","lat":40.66388,"lon":43.97089},{"name":"Parakar","country":"AM","lat":40.16388,"lon":44.4057},{"name":"Paravakar","country":"AM","lat":40.98248,"lon":45.36696},{"name":"Parpi","country":"AM","lat":40.32231,"lon":44.31141},{"name":"Pemzashen","country":"AM","lat":40.58612,"lon":43.94311},{"name":"Pokr Mantash","country":"AM","lat":40.64026,"lon":44.04666},{"name":"Pokr Vedi","country":"AM","lat":39.90289,"lon":44.6029},{"name":"Proshyan","country":"AM","lat":40.24731,"lon":44.41949},{"name":"Pshatavan","country":"AM","lat":40.03888,"lon":44.06671},{"name":"Ptghni","country":"AM","lat":40.25681,"lon":44.58195},{"name":"Ptghunk","country":"AM","lat":40.16388,"lon":44.36389},{"name":"Ranchpar","country":"AM","lat":40.02789,"lon":44.36951},{"name":"Rind","country":"AM","lat":39.76111,"lon":45.17792},{"name":"Sarahart","country":"AM","lat":40.87043,"lon":44.21407},{"name":"Saralanj","country":"AM","lat":40.62116,"lon":44.02041},{"name":"Saramej","country":"AM","lat":40.77487,"lon":44.2222},{"name":"Saratak","country":"AM","lat":40.6709,"lon":43.87231},{"name":"Sarchapet","country":"AM","lat":41.196,"lon":44.38432},{"name":"Sardarapat","country":"AM","lat":40.13206,"lon":44.00969},{"name":"Sarigyugh","country":"AM","lat":41.03531,"lon":45.14486},{"name":"Sarnaghbyur","country":"AM","lat":40.52368,"lon":43.91248},{"name":"Sarukhan","country":"AM","lat":40.29169,"lon":45.13068},{"name":"Sasunik","country":"AM","lat":40.25012,"lon":44.34448},{"name":"Sayat-Nova","country":"AM","lat":40.07507,"lon":44.40008},{"name":"Sevan","country":"AM","lat":40.548,"lon":44.95314},{"name":"Sevkar","country":"AM","lat":41.01599,"lon":45.14185},{"name":"Shahumyan","country":"AM","lat":39.94171,"lon":44.57233},{"name":"Shahumyan","country":"AM","lat":40.21393,"lon":44.30011},{"name":"Shahumyan","country":"AM","lat":40.77482,"lon":44.54596},{"name":"Shaki","country":"AM","lat":39.56499,"lon":45.99861},{"name":"Shamiram","country":"AM","lat":40.27654,"lon":44.09846},{"name":"Shatin","country":"AM","lat":39.83612,"lon":45.30292},{"name":"Shenavan","country":"AM","lat":40.48328,"lon":44.38348},{"name":"Shenavan","country":"AM","lat":40.05548,"lon":43.93048},{"name":"Shengavit","country":"AM","lat":40.1557,"lon":44.4779},{"name":"Shenik","country":"AM","lat":40.213,"lon":43.77033},{"name":"Shinuhayr","country":"AM","lat":39.4367,"lon":46.31787},{"name":"Shirak","country":"AM","lat":40.84042,"lon":43.91582},{"name":"Shirakamut","country":"AM","lat":40.85287,"lon":44.16366},{"name":"Shnogh","country":"AM","lat":41.14693,"lon":44.84043},{"name":"Sis","country":"AM","lat":40.05829,"lon":44.38892},{"name":"Sisavan","country":"AM","lat":39.90802,"lon":44.66721},{"name":"Sisian","country":"AM","lat":39.52191,"lon":46.02696},{"name":"Solak","country":"AM","lat":40.46252,"lon":44.70709},{"name":"Sotk","country":"AM","lat":40.20007,"lon":45.86951},{"name":"Spandaryan","country":"AM","lat":40.66105,"lon":44.01551},{"name":"Spitak","country":"AM","lat":40.83131,"lon":44.27019},{"name":"Stepanavan","country":"AM","lat":41.00995,"lon":44.38531},{"name":"Surenavan","country":"AM","lat":39.79449,"lon":44.77508},{"name":"Tairov","country":"AM","lat":40.16078,"lon":44.43435},{"name":"Talin","country":"AM","lat":40.39172,"lon":43.87793},{"name":"Tandzut","country":"AM","lat":40.06952,"lon":44.07788},{"name":"Taronik","country":"AM","lat":40.13367,"lon":44.19957},{"name":"Tashir","country":"AM","lat":41.11922,"lon":44.28649},{"name":"Tavush","country":"AM","lat":40.91763,"lon":45.40528},{"name":"Tegh","country":"AM","lat":39.55826,"lon":46.48054},{"name":"Teghut","country":"AM","lat":40.77851,"lon":44.93838},{"name":"Tsaghkaber","country":"AM","lat":40.79849,"lon":44.10144},{"name":"Tsaghkadzor","country":"AM","lat":40.5325,"lon":44.72323},{"name":"Tsaghkahovit","country":"AM","lat":40.63883,"lon":44.22252},{"name":"Tsaghkalanj","country":"AM","lat":40.20007,"lon":44.23053},{"name":"Tsaghkunk","country":"AM","lat":40.57788,"lon":44.87793},{"name":"Tsaghkunk","country":"AM","lat":40.18048,"lon":44.27228},{"name":"Tsakkar","country":"AM","lat":40.17354,"lon":45.22201},{"name":"Tsiatsan","country":"AM","lat":40.1861,"lon":44.26947},{"name":"Tsovagyugh","country":"AM","lat":40.63348,"lon":44.96112},{"name":"Tsovak","country":"AM","lat":40.18254,"lon":45.63286},{"name":"Tsovasar","country":"AM","lat":40.1382,"lon":45.19096},{"name":"Tsovazard","country":"AM","lat":40.4751,"lon":45.05011},{"name":"Tsovinar","country":"AM","lat":40.15959,"lon":45.46786},{"name":"Ttujur","country":"AM","lat":40.64644,"lon":45.31586},{"name":"Tumanyan","country":"AM","lat":41.0019,"lon":44.6494},{"name":"Ujan","country":"AM","lat":40.29671,"lon":44.205},{"name":"Urtsadzor","country":"AM","lat":39.91949,"lon":44.82507},{"name":"Ushi","country":"AM","lat":40.34729,"lon":44.37512},{"name":"Vagharshapat","country":"AM","lat":40.16557,"lon":44.29462},{"name":"Vaghashen","country":"AM","lat":40.13611,"lon":45.33069},{"name":"Vahagni","country":"AM","lat":40.90698,"lon":44.60873},{"name":"Vanadzor","country":"AM","lat":40.80456,"lon":44.4939},{"name":"Vanand","country":"AM","lat":40.10307,"lon":43.81506},{"name":"Vanashen","country":"AM","lat":39.90008,"lon":44.6889},{"name":"Vardablur","country":"AM","lat":40.97083,"lon":44.50889},{"name":"Vardadzor","country":"AM","lat":40.1875,"lon":45.19389},{"name":"Vardanashen","country":"AM","lat":40.05242,"lon":44.19014},{"name":"Vardenik","country":"AM","lat":40.13722,"lon":45.42914},{"name":"Vardenis","country":"AM","lat":40.1827,"lon":45.73156},{"name":"Varser","country":"AM","lat":40.55548,"lon":44.90832},{"name":"Vayk","country":"AM","lat":39.69026,"lon":45.46919},{"name":"Vedi","country":"AM","lat":39.91291,"lon":44.72083},{"name":"Verin Artashat","country":"AM","lat":39.99731,"lon":44.58893},{"name":"Verin Dvin","country":"AM","lat":40.02393,"lon":44.5924},{"name":"Verin Getashen","country":"AM","lat":40.13068,"lon":45.25293},{"name":"Verin Karmiraghbyur","country":"AM","lat":40.88044,"lon":45.44159},{"name":"Verishen","country":"AM","lat":39.53117,"lon":46.31829},{"name":"Vernashen","country":"AM","lat":39.79236,"lon":45.36389},{"name":"Voskehask","country":"AM","lat":40.76426,"lon":43.77474},{"name":"Voskehat","country":"AM","lat":40.27789,"lon":44.27508},{"name":"Voskehat","country":"AM","lat":40.14172,"lon":44.33069},{"name":"Vosketap","country":"AM","lat":39.88114,"lon":44.64917},{"name":"Voskevan","country":"AM","lat":41.12081,"lon":45.06381},{"name":"Voskevaz","country":"AM","lat":40.27508,"lon":44.30011},{"name":"Vostan","country":"AM","lat":39.96515,"lon":44.55937},{"name":"Yeghegis","country":"AM","lat":39.8723,"lon":45.3575},{"name":"Yeghegnadzor","country":"AM","lat":39.76389,"lon":45.33239},{"name":"Yeghegnavan","country":"AM","lat":39.83893,"lon":44.61951},{"name":"Yeghegnut","country":"AM","lat":40.08893,"lon":44.16669},{"name":"Yeghvard","country":"AM","lat":40.32293,"lon":44.48418},{"name":"Yelpin","country":"AM","lat":39.80832,"lon":45.10985},{"name":"Yeranos","country":"AM","lat":40.20428,"lon":45.19209},{"name":"Yeraskhahun","country":"AM","lat":40.07233,"lon":44.21948},{"name":"Yerazgavors","country":"AM","lat":40.70288,"lon":43.77649},{"name":"Yerevan","country":"AM","lat":40.18111,"lon":44.51361},{"name":"Zangakatun","country":"AM","lat":39.82233,"lon":45.04169},{"name":"Zar","country":"AM","lat":40.25848,"lon":44.73328},{"name":"Zaritap","country":"AM","lat":39.63892,"lon":45.51111},{"name":"Zartonk","country":"AM","lat":40.10828,"lon":44.16388},{"name":"Zolakar","country":"AM","lat":40.12512,"lon":45.38068},{"name":"Zorak","country":"AM","lat":40.09168,"lon":44.39447},{"name":"Zoravan","country":"AM","lat":40.35553,"lon":44.52228},{"name":"Zovaber","country":"AM","lat":40.56671,"lon":44.79028},{"name":"Zovuni","country":"AM","lat":40.23307,"lon":44.51129}]